UKGAppHealth/UKGAppHealth.py
UKGAppHealth/__init__.py
UKGAppHealth-1.2.3.dist-info/METADATA
UKGAppHealth-1.2.3.dist-info/WHEEL
UKGAppHealth-1.2.3.dist-info/top_level.txt
UKGAppHealth-1.2.3.dist-info/RECORD
