Metadata-Version: 2.2
Name: UKGAppHealth
Version: 1.2.3
Summary: Python library for monitoring health checks on running apps
Author: Reinas Balakauskas
Dynamic: author
Dynamic: summary
